homelypy/__init__.py
homelypy/devices.py
homelypy/homely.py
homelypy/location_Avskåkålia.json
homelypy/states.py
homelypy-0.1.15.dist-info/METADATA
homelypy-0.1.15.dist-info/WHEEL
homelypy-0.1.15.dist-info/licenses/LICENCE
homelypy-0.1.15.dist-info/RECORD
